.gitignore
.travis.yml
CHANGES.txt
README.rst
setup.cfg
setup.py
player/__init__.py
player/formatter.py
player/layer.py
player/layout_impl.py
player/message.py
player/renderer.py
player/script.py
player.egg-info/PKG-INFO
player.egg-info/SOURCES.txt
player.egg-info/dependency_links.txt
player.egg-info/entry_points.txt
player.egg-info/not-zip-safe
player.egg-info/requires.txt
player.egg-info/top_level.txt
player/templates/message/error.jinja2
player/templates/message/info.jinja2
player/templates/message/success.jinja2
player/templates/message/warning.jinja2
player/tests/base.py
player/tests/test-layout-html.pt
player/tests/test-layout.pt
player/tests/test_custom.py
player/tests/test_formatter.py
player/tests/test_layer.py
player/tests/test_layout.py
player/tests/test_message.py
player/tests/test_order.py
player/tests/test_renderer.py
player/tests/test_script.py
player/tests/bundle/dir1/view.pt
player/tests/dir1/actions.pt
player/tests/dir1/view.pt
player/tests/message/custom.pt